trytond/modules/cashbook_media/README.rst
trytond/modules/cashbook_media/__init__.py
trytond/modules/cashbook_media/line.py
trytond/modules/cashbook_media/line.xml
trytond/modules/cashbook_media/message.xml
trytond/modules/cashbook_media/tryton.cfg
trytond/modules/cashbook_media/versiondep.txt
trytond/modules/cashbook_media/locale/de.po
trytond/modules/cashbook_media/locale/en.po
trytond/modules/cashbook_media/tests/__init__.py
trytond/modules/cashbook_media/tests/img_data.py
trytond/modules/cashbook_media/tests/test_line.py
trytond/modules/cashbook_media/view/line_form.xml
mds_cashbook_media-7.0.4.dist-info/METADATA
mds_cashbook_media-7.0.4.dist-info/WHEEL
mds_cashbook_media-7.0.4.dist-info/entry_points.txt
mds_cashbook_media-7.0.4.dist-info/top_level.txt
mds_cashbook_media-7.0.4.dist-info/RECORD
