Metadata-Version: 2.1
Name: mds-cashbook-media
Version: 7.0.4
Summary: Tryton module to add a file-field to cashbook.
Home-page: https://www.m-ds.de/
Author: martin-data services
Author-email: service@m-ds.de
License: GPL-3
Download-URL: https://scmdev.m-ds.de/Tryton/Extra/cashbook_media
Keywords: tryton cashbook pdf png image file
Platform: UNKNOWN
Classifier: Development Status :: 5 - Production/Stable
Classifier: Environment :: Plugins
Classifier: Framework :: Tryton
Classifier: Intended Audience :: Developers
Classifier: Intended Audience :: Customer Service
Classifier: Intended Audience :: Information Technology
Classifier: Intended Audience :: Financial and Insurance Industry
Classifier: Topic :: Office/Business
Classifier: Topic :: Office/Business :: Financial :: Accounting
Classifier: Natural Language :: German
Classifier: Natural Language :: English
Classifier: Operating System :: OS Independent
Classifier: License :: OSI Approved :: GNU General Public License (GPL)
Classifier: Programming Language :: Python :: 3.7
Classifier: Programming Language :: Python :: 3.8
Classifier: Programming Language :: Python :: 3.9
Requires-Dist: Pillow
Requires-Dist: mds-cashbook (<=7.0.999,>=7.0.31)
Requires-Dist: python-magic (>=0.4.24)
Requires-Dist: trytond (<7.1,>=7.0)
